{"_type":"export","__export_format":4,"__export_date":"2020-08-13T23:02:56.417Z","__export_source":"insomnia.desktop.app:v2020.3.3","resources":[{"_id":"req_4c19e3b9b11a4befa0341fcf39407237","authentication":{},"body":{},"created":1597096790789,"description":"","headers":[],"isPrivate":false,"metaSortKey":-1597096790790,"method":"GET","modified":1597096847024,"name":"Show","parameters":[],"parentId":"fld_e5df761c3c6e48d781110050ad4e470f","settingDisableRenderRequestBody":false,"settingEncodeUrl":true,"settingFollowRedirects":"global","settingRebuildPath":true,"settingSendCookies":true,"settingStoreCookies":true,"url":"http://localhost:3333/user","_type":"request"},{"_id":"fld_e5df761c3c6e48d781110050ad4e470f","created":1594254343964,"description":"","environment":{},"environmentPropertyOrder":null,"metaSortKey":-1594254343964,"modified":1594254343964,"name":"User","parentId":"wrk_6b64b91561eb4064ad38c1222ec3c48a","_type":"request_group"},{"_id":"wrk_6b64b91561eb4064ad38c1222ec3c48a","created":1594254319151,"description":"","modified":1594850169638,"name":"User Rec","parentId":null,"scope":null,"_type":"workspace"},{"_id":"req_bebdd7ac3fd44b52b40c8f5053ccc086","authentication":{},"body":{"mimeType":"application/json","text":"{\n\t\"identification\": \"07592367980\",\n\t\"firstName\": \"Vagner\",\n  \"lastName\": \"Castro\",\n  \"email\": \"vagner.bcastro1@gmail.com\",\n  \"phone\": \"45999481153\",\n  \"password\": \"password\"\n}"},"created":1594254340077,"description":"","headers":[{"id":"pair_f44ec2e1df3641e2b25d491078d2d763","name":"Content-Type","value":"application/json"}],"isPrivate":false,"metaSortKey":-1594254343914,"method":"POST","modified":1597359264879,"name":"Add ","parameters":[],"parentId":"fld_e5df761c3c6e48d781110050ad4e470f","settingDisableRenderRequestBody":false,"settingEncodeUrl":true,"settingFollowRedirects":"global","settingRebuildPath":true,"settingSendCookies":true,"settingStoreCookies":true,"url":"http://localhost:3333/user","_type":"request"},{"_id":"env_3fcb0f94ccd3355e9fe73b72b26c186c5881070e","color":null,"created":1594254319216,"data":{},"dataPropertyOrder":null,"isPrivate":false,"metaSortKey":1594254319216,"modified":1594254319216,"name":"Base Environment","parentId":"wrk_6b64b91561eb4064ad38c1222ec3c48a","_type":"environment"},{"_id":"jar_3fcb0f94ccd3355e9fe73b72b26c186c5881070e","cookies":[],"created":1594254319219,"modified":1594254319219,"name":"Default Jar","parentId":"wrk_6b64b91561eb4064ad38c1222ec3c48a","_type":"cookie_jar"},{"_id":"spc_b9d7424339644f6c81439dfe95d4a792","contentType":"yaml","contents":"","created":1594850152791,"fileName":"Help Call","modified":1594850152791,"parentId":"wrk_6b64b91561eb4064ad38c1222ec3c48a","_type":"api_spec"}]}